{
  "doc_id": "14226",
  "scraped_at": "2026-06-13T14:42:02.492235",
  "species": "Worm-eating Warbler",
  "acc_no": "52-93-119",
  "reporter_name": "Mark Janos",
  "address": "",
  "city": "",
  "state": "",
  "zip": "",
  "reporter_email": "",
  "other_observers": "",
  "species_name": "Worm-eating Warbler",
  "first_date": "5/10/1988 8:00:00 AM",
  "last_date": "5/11/1988 8:00:00 AM",
  "duration": "",
  "county": "Otero",
  "specific_location": "La Junta",
  "number_of_birds": "1",
  "age": "Unknown",
  "sex": "Unknown",
  "plumage": "Other/Unknown",
  "description": "",
  "photographer": "Photographer: Mark Janos",
  "photos_text": "PDF",
  "uploads_text": "14226_wewa-52-93-119.pdf",
  "date_submitted": "9/7/2024 9:44:00 PM",
  "attachments": [
    {
      "filename": "14226_wewa-52-93-119.pdf",
      "url": "/RecordUploads/14226/14226_wewa-52-93-119.pdf"
    }
  ]
}