{
  "doc_id": "1381",
  "scraped_at": "2026-06-13T14:47:19.953853",
  "species": "Pine Warbler",
  "acc_no": "2010-008",
  "reporter_name": "Brandon K Percival",
  "address": "406 Chatfield Drive,",
  "city": "Colorado Springs,",
  "state": "CO",
  "zip": "80911",
  "reporter_email": "flammowl17@gmail.com",
  "other_observers": "Bill Maynard, Clif Smith, Pearle Sandstorm-Smith; I found bird. It was seen by Glenn Walbek, Loch Kilpatrick, Dan and John Maynard on 01/22/2010. Seen by Mark Peterson and Gene Rutherford on 01/23/2010. Seen by Paul and Polly Neldner on 01/24/2010. Seen by John Dummond, Duane Nelson, Stan Oswald on",
  "species_name": "Pine Warbler",
  "first_date": "1/25/2010",
  "last_date": "",
  "duration": "off and on for over two hours",
  "county": "Pueblo",
  "specific_location": "Pueblo City Park",
  "number_of_birds": "1",
  "age": "Unknown",
  "sex": "Female",
  "plumage": "Other/Unknown",
  "description": "see other documentationBehaviors: see other documentationCall: see other documentationPlumage: first year",
  "photographer": "Photographer: Brandon Percival, Brandon K Percival, Brandon K Percival, Brandon K Percival, Brandon K Percival",
  "photos_text": "Photos |",
  "uploads_text": "1381_abcd0696.JPG\n1381_abcd1704.JPG\n1381_abcd2Pine Warbler 9.jpg\n1381_abcd3Pine Warbler 2 small.jpg\n1381_abcd4Pine Warbler 3 small.jpg",
  "date_submitted": "1/26/2010 2:54:00 PM",
  "attachments": [
    {
      "filename": "1381_abcd0696.JPG",
      "url": "/RecordUploads/1381/1381_abcd0696.JPG"
    },
    {
      "filename": "1381_abcd1704.JPG",
      "url": "/RecordUploads/1381/1381_abcd1704.JPG"
    },
    {
      "filename": "1381_abcd2Pine Warbler 9.jpg",
      "url": "/RecordUploads/1381/1381_abcd2Pine Warbler 9.jpg"
    },
    {
      "filename": "1381_abcd3Pine Warbler 2 small.jpg",
      "url": "/RecordUploads/1381/1381_abcd3Pine Warbler 2 small.jpg"
    },
    {
      "filename": "1381_abcd4Pine Warbler 3 small.jpg",
      "url": "/RecordUploads/1381/1381_abcd4Pine Warbler 3 small.jpg"
    },
    {
      "filename": "1381_abcd2Pine%20Warbler%209.jpg",
      "url": "/RecordUploads/1381/1381_abcd2Pine%20Warbler%209.jpg"
    },
    {
      "filename": "1381_abcd3Pine%20Warbler%202%20small.jpg",
      "url": "/RecordUploads/1381/1381_abcd3Pine%20Warbler%202%20small.jpg"
    },
    {
      "filename": "1381_abcd4Pine%20Warbler%203%20small.jpg",
      "url": "/RecordUploads/1381/1381_abcd4Pine%20Warbler%203%20small.jpg"
    }
  ]
}