{
  "doc_id": "2531",
  "scraped_at": "2026-06-13T14:39:40.653475",
  "species": "Red-necked Grebe",
  "acc_no": "2013-181",
  "reporter_name": "Lee Farrell",
  "address": "",
  "city": "",
  "state": "",
  "zip": "",
  "reporter_email": "",
  "other_observers": "Linda Farrell, on 7/13/13 - Chuck Hundertmark, Paul Slingsby, Nina Routh",
  "species_name": "Red-necked Grebe",
  "first_date": "7/10/2013",
  "last_date": "7/10/2013",
  "duration": "Hour and a half",
  "county": "Jackson",
  "specific_location": "Lake John",
  "number_of_birds": "1",
  "age": "Unknown",
  "sex": "Unknown",
  "plumage": "Other/Unknown",
  "description": "Large Grebe, dark grey/black back and top of head. Head double crested. White face, red neck.Behavior: Observed on several occasions over a four day period. Floating on the surface, moving around the lake, foraging, diving to feed on occasion. Stayed alone, did not mingle with numerous Western Grebes courting and feeding on the lake.Call: N/APlumage: Summer breeding",
  "photographer": "Photographer: Lee Farrell, Lee Farrell",
  "photos_text": "Photos |",
  "uploads_text": "2531_abcd0IMG_1141July2013NorthPark.JPG\n2531_abcd1IMG_1259July2013NorthParkC.JPG",
  "date_submitted": "7/17/2013 9:38:00 PM",
  "attachments": [
    {
      "filename": "2531_abcd0IMG_1141July2013NorthPark.JPG",
      "url": "/RecordUploads/2531/2531_abcd0IMG_1141July2013NorthPark.JPG"
    },
    {
      "filename": "2531_abcd1IMG_1259July2013NorthParkC.JPG",
      "url": "/RecordUploads/2531/2531_abcd1IMG_1259July2013NorthParkC.JPG"
    }
  ]
}