{
  "doc_id": "16382",
  "scraped_at": "2026-06-13T14:48:27.149508",
  "species": "Eurasian Wigeon",
  "acc_no": "8-86-3",
  "reporter_name": "Mark Janos, Laurens Halsey, Peter Gent",
  "address": "",
  "city": "",
  "state": "",
  "zip": "",
  "reporter_email": "",
  "other_observers": "",
  "species_name": "Eurasian Wigeon",
  "first_date": "1/26/1986 9:40:00 AM",
  "last_date": "2/1/1986 10:00:00 AM",
  "duration": "",
  "county": "Adams",
  "specific_location": "Barr Lake State Park",
  "number_of_birds": "1",
  "age": "Unknown",
  "sex": "Unknown",
  "plumage": "Other/Unknown",
  "description": "",
  "photographer": "Photographer: Mark Janos, Laurens Halsey, Peter Gent",
  "photos_text": "PDF",
  "uploads_text": "16382_euwi-8-86-3.pdf",
  "date_submitted": "3/1/2026 4:21:00 PM",
  "attachments": [
    {
      "filename": "16382_euwi-8-86-3.pdf",
      "url": "/RecordUploads/16382/16382_euwi-8-86-3.pdf"
    }
  ]
}