{
  "doc_id": "14128",
  "scraped_at": "2026-06-13T14:49:55.932518",
  "species": "Philadelphia Vireo",
  "acc_no": "2002-125",
  "reporter_name": "Ric Olson",
  "address": "",
  "city": "",
  "state": "",
  "zip": "",
  "reporter_email": "",
  "other_observers": "",
  "species_name": "Philadelphia Vireo",
  "first_date": "5/19/2002 8:30:00 AM",
  "last_date": "5/19/2002 8:35:00 AM",
  "duration": "",
  "county": "Weld",
  "specific_location": "Crow Valley Campground",
  "number_of_birds": "1",
  "age": "Unknown",
  "sex": "Unknown",
  "plumage": "Other/Unknown",
  "description": "",
  "photographer": "Photographer: Ric Olson",
  "photos_text": "PDF",
  "uploads_text": "14128_phvi-2002-125.pdf",
  "date_submitted": "8/1/2024 3:22:00 PM",
  "attachments": [
    {
      "filename": "14128_phvi-2002-125.pdf",
      "url": "/RecordUploads/14128/14128_phvi-2002-125.pdf"
    }
  ]
}