{
  "doc_id": "1200",
  "scraped_at": "2026-06-13T14:49:40.086426",
  "species": "Eurasian Wigeon",
  "acc_no": "2009-010",
  "reporter_name": "C W",
  "address": "",
  "city": "",
  "state": "",
  "zip": "",
  "reporter_email": "",
  "other_observers": "Andrew Spencer came out and saw the bird shortly after I found it, I was still there when he got there.; I was the original finder of the bird. Several others saw the bird.",
  "species_name": "Eurasian Wigeon",
  "first_date": "3/4/2009",
  "last_date": "",
  "duration": "1 hour",
  "county": "Larimer",
  "specific_location": "Swede Lake, which is on the southeast side of Fossil Creek Reservoir",
  "number_of_birds": "1",
  "age": "Unknown",
  "sex": "Male",
  "plumage": "Other/Unknown",
  "description": "Gray bill with a black tip. Red head with a yellowish buffy forehead. Pinkish breast. Gray sides and back. With a white spot in the wing and on the side towards the back of the bird. The back of the bird and the tail was black.Behaviors: Swam around the whole time I was watching it. It was following a female American Wigeon most of the time. It called occasionally.Call: It gave a wigeon type call, but it was different than any American Wigeon that I had heard. It sound higher and it was a single note.Plumage: Adult",
  "photographer": "Photographer: Cole Wild",
  "photos_text": "Photos |",
  "uploads_text": "1200_abcd0IMG_2972new.jpg",
  "date_submitted": "3/26/2009 10:57:00 PM",
  "attachments": [
    {
      "filename": "1200_abcd0IMG_2972new.jpg",
      "url": "/RecordUploads/1200/1200_abcd0IMG_2972new.jpg"
    }
  ]
}