{
  "doc_id": "14167",
  "scraped_at": "2026-06-13T14:42:48.088181",
  "species": "Yellow-throated Vireo",
  "acc_no": "51-90-45",
  "reporter_name": "Joan Humphrey, Stephen Bailey",
  "address": "",
  "city": "",
  "state": "",
  "zip": "",
  "reporter_email": "",
  "other_observers": "",
  "species_name": "Yellow-throated Vireo",
  "first_date": "6/20/1990 8:50:00 AM",
  "last_date": "6/20/1990 9:15:00 AM",
  "duration": "",
  "county": "Weld",
  "specific_location": "Crow Valley Campground",
  "number_of_birds": "1",
  "age": "Unknown",
  "sex": "Unknown",
  "plumage": "Other/Unknown",
  "description": "",
  "photographer": "Photographer: Joan Humphrey, Stephen Bailey",
  "photos_text": "PDF",
  "uploads_text": "14167_ytvi-51-90-45.pdf",
  "date_submitted": "8/17/2024 6:39:00 PM",
  "attachments": [
    {
      "filename": "14167_ytvi-51-90-45.pdf",
      "url": "/RecordUploads/14167/14167_ytvi-51-90-45.pdf"
    }
  ]
}