{
  "doc_id": "13706",
  "scraped_at": "2026-06-13T14:34:38.818777",
  "species": "Thick-billed Kingbird",
  "acc_no": "2004-033",
  "reporter_name": "P J Mestas",
  "address": "",
  "city": "",
  "state": "",
  "zip": "",
  "reporter_email": "",
  "other_observers": "",
  "species_name": "Thick-billed Kingbird",
  "first_date": "7/3/2004 6:45:00 AM",
  "last_date": "7/3/2004 6:50:00 AM",
  "duration": "",
  "county": "Elbert",
  "specific_location": "Elizabeth",
  "number_of_birds": "1",
  "age": "Unknown",
  "sex": "Unknown",
  "plumage": "Other/Unknown",
  "description": "",
  "photographer": "Photographer: P J Mestas",
  "photos_text": "PDF",
  "uploads_text": "13706_tbki-2004-33.pdf",
  "date_submitted": "2/5/2024 2:41:00 PM",
  "attachments": [
    {
      "filename": "13706_tbki-2004-33.pdf",
      "url": "/RecordUploads/13706/13706_tbki-2004-33.pdf"
    }
  ]
}