{
  "doc_id": "16454",
  "scraped_at": "2026-06-13T14:49:20.765298",
  "species": "Glossy Ibis",
  "acc_no": "1998-013",
  "reporter_name": "Ric Olson",
  "address": "",
  "city": "",
  "state": "",
  "zip": "",
  "reporter_email": "",
  "other_observers": "",
  "species_name": "Glossy Ibis",
  "first_date": "4/18/1998 12:10:00 PM",
  "last_date": "4/18/1998 12:25:00 PM",
  "duration": "",
  "county": "Adams",
  "specific_location": "Barr Lake State Park",
  "number_of_birds": "1",
  "age": "Unknown",
  "sex": "Unknown",
  "plumage": "Other/Unknown",
  "description": "",
  "photographer": "Photographer: Ric Olson",
  "photos_text": "PDF",
  "uploads_text": "16454_glib-1998-13.pdf",
  "date_submitted": "4/6/2026 4:34:00 PM",
  "attachments": [
    {
      "filename": "16454_glib-1998-13.pdf",
      "url": "/RecordUploads/16454/16454_glib-1998-13.pdf"
    }
  ]
}