{
  "doc_id": "6336",
  "scraped_at": "2026-06-13T14:40:24.943237",
  "species": "Arctic Tern",
  "acc_no": "2015-108",
  "reporter_name": "Tom Behnfield",
  "address": "8160 W Baker Avenue,",
  "city": "Lakewood,",
  "state": "CO",
  "zip": "80227",
  "reporter_email": "behnfield@gmail.com",
  "other_observers": "Debbie Behnfield, Matt Clark, Susan Bonfiglio, Gwen Moore, Frank Ferrell, Lee & Linda Farrell, Scott Somershoe, Dan Stringer, Bill & Woody from Texas",
  "species_name": "Arctic Tern",
  "first_date": "10/2/2015 5:25:00 PM",
  "last_date": "10/3/2015 12:00:00 PM",
  "duration": "1.5 Hours",
  "county": "Douglas",
  "specific_location": "Chatfield State Park (Douglas Portion)",
  "number_of_birds": "1",
  "age": "Immature",
  "sex": "Unknown",
  "plumage": "Transitional",
  "description": "This appears to be a worn Juvenile. Distinguishing this bird from the Common Terns I viewed a couple of weeks ago are rounder head, lighter carpal bar & wing pattern (white secondaries & white-tipped greater coverts, & translucent, thin black-tipped primaries.) There was just one Tern. It flew in, stayed around a couple of feet in from the shoreline and mostly preened for 20-30 minutes. It would fly away for a minute and return, then it left for 30 minutes or so and returned to the same approximate spot on the Chatfield marina Sandspit. On October 3, 2015 our group was able to approach the bird to within 50 feet and capture some okay images.",
  "photographer": "Photographer: Tom Behnfield, Tom Behnfield",
  "photos_text": "Photos |",
  "uploads_text": "6336_Tern_2.jpg\n6336_Tern_Wings_3.jpg",
  "date_submitted": "2/14/2016 3:19:00 PM",
  "attachments": [
    {
      "filename": "6336_Tern_2.jpg",
      "url": "/RecordUploads/6336/6336_Tern_2.jpg"
    },
    {
      "filename": "6336_Tern_Wings_3.jpg",
      "url": "/RecordUploads/6336/6336_Tern_Wings_3.jpg"
    }
  ]
}