{
  "doc_id": "2058",
  "scraped_at": "2026-06-13T14:34:04.238091",
  "species": "Northern Waterthrush",
  "acc_no": "2012-229",
  "reporter_name": "Polly Neldner",
  "address": "PO Box 358,",
  "city": "La Veta,",
  "state": "CO",
  "zip": "81055",
  "reporter_email": "pollywren@gmail.com",
  "other_observers": "Paul Neldner; I believe we are the original finders of this bird.",
  "species_name": "Northern Waterthrush",
  "first_date": "8/17/2012",
  "last_date": "",
  "duration": "Around 5 minutes",
  "county": "Alamosa",
  "specific_location": "Area 92 of Blanca Wetlands",
  "number_of_birds": "1",
  "age": "Unknown",
  "sex": "Unknown",
  "plumage": "Other/Unknown",
  "description": "White supercilium, narrow toward rear of supercilium. Dense black streaks across breast, extending down the flanks. Approximately 6 inches long. Brown crown neck and back. Squarish tail. Legs were relatively long and appeared \"pinkish\". Relatively thin \"sharp looking\" beak.Behaviors: Bird was walking and, for short distances, running along the banks of the waterway, bobbing it's tail.Call: None heardPlumage: Yellow adult",
  "photographer": "Photographer: Polly Neldner, Polly Wren Neldner, Polly Wren Neldner",
  "photos_text": "Photos |",
  "uploads_text": "2058_abcd0IMG_0226.JPG\n2058_abcd1IMG_0227.JPG\n2058_abcd2IMG_0230.JPG",
  "date_submitted": "8/21/2012 1:18:00 PM",
  "attachments": [
    {
      "filename": "2058_abcd0IMG_0226.JPG",
      "url": "/RecordUploads/2058/2058_abcd0IMG_0226.JPG"
    },
    {
      "filename": "2058_abcd1IMG_0227.JPG",
      "url": "/RecordUploads/2058/2058_abcd1IMG_0227.JPG"
    },
    {
      "filename": "2058_abcd2IMG_0230.JPG",
      "url": "/RecordUploads/2058/2058_abcd2IMG_0230.JPG"
    }
  ]
}