{
  "doc_id": "1175",
  "scraped_at": "2026-06-13T14:35:40.562092",
  "species": "Ancient Murrelet",
  "acc_no": "2008-134",
  "reporter_name": "Rick Clawges",
  "address": "",
  "city": "",
  "state": "",
  "zip": "",
  "reporter_email": "",
  "other_observers": "Tamara Ivahnenko; Rick Clawges",
  "species_name": "Ancient Murrelet",
  "first_date": "11/16/2008",
  "last_date": "",
  "duration": "10 minutes",
  "county": "Pueblo",
  "specific_location": "Pueblo Reservoir. On the south side at the end of a road that disappears at the reservoir's shore. This paved road separates the Reservoir land from the State Wildlife Area.The bird was in a cove in the first canyon to the east, closer to the entrance of the canyon (where it meets the reservoir proper). Mark Yeager called it Peck Creek canyon when I mentioned it to him.",
  "number_of_birds": "1",
  "age": "Unknown",
  "sex": "Unknown",
  "plumage": "Other/Unknown",
  "description": "The bird had an alcid shape, and was alternately floating and diving. It never flew when in our view. It had a light grey back, short, light-colored bill, and a dark black head with a bright white neck. The most distinctive feature was the bright white patch (hook-shaped) behind its eye, which helped us distinguish it from other possible murrelets and flagged its plumage as nonbreeding.Behaviors: The bird was in view for at least 10 minutes, diving and floating. It's body was low on the water, including its head. It was a fairly cooperative subject to view, diving when we got too close but surfacing not too far away. I think the closest we may have gotten to it was 50 feet (we were in a canoe on Pueblo Reservoir).Call: None heard.Plumage: Nonbreeding",
  "photographer": "Photographer: Rick Clawges, Rick Clawges, Rick Clawges, Rick Clawges",
  "photos_text": "Photos |",
  "uploads_text": "1175_abcd0Ancient_Murrelet.JPG\n1175_abcd1IMG_2160.JPG\n1175_abcd2IMG_2156.JPG\n1175_abcd3IMG_2158.JPG",
  "date_submitted": "1/19/2009 5:20:00 PM",
  "attachments": [
    {
      "filename": "1175_abcd0Ancient_Murrelet.JPG",
      "url": "/RecordUploads/1175/1175_abcd0Ancient_Murrelet.JPG"
    },
    {
      "filename": "1175_abcd1IMG_2160.JPG",
      "url": "/RecordUploads/1175/1175_abcd1IMG_2160.JPG"
    },
    {
      "filename": "1175_abcd2IMG_2156.JPG",
      "url": "/RecordUploads/1175/1175_abcd2IMG_2156.JPG"
    },
    {
      "filename": "1175_abcd3IMG_2158.JPG",
      "url": "/RecordUploads/1175/1175_abcd3IMG_2158.JPG"
    }
  ]
}