{
  "acc_no": "52-85-33",
  "year": "1985",
  "location": "Wheat Ridge Greenbelt",
  "county": "Jefferson",
  "observers": "Duane Nelson",
  "comments": "",
  "citations": "Gent, P.  1985 Report of the CBRC. CFO Journal 20(3-4), 44-50.",
  "documentations": [
    {
      "doc_id": "16081",
      "reporter": "Duane Nelson",
      "date": "8/20/1985",
      "has_photos": false,
      "doc_url": "https://cobrc.org/Reports/PrintDoc.aspx?DocID=16081"
    }
  ],
  "scraped_at": "2026-06-13T14:45:53.891909"
}