{
  "doc_id": "2544",
  "scraped_at": "2026-06-13T14:49:17.289866",
  "species": "Golden-crowned Sparrow",
  "acc_no": "2012-195",
  "reporter_name": "Doug Faulkner",
  "address": "6035 Parfet St.,",
  "city": "ARVADA,",
  "state": "CO",
  "zip": "80004-4648",
  "reporter_email": "zebrilus@gmail.com",
  "other_observers": "",
  "species_name": "Golden-crowned Sparrow",
  "first_date": "2/18/2013 9:00:00 AM",
  "last_date": "2/18/2013 10:00:00 AM",
  "duration": "10 minutes",
  "county": "Jefferson",
  "specific_location": "Red Rocks Park",
  "number_of_birds": "1",
  "age": "Adult",
  "sex": "Unknown",
  "plumage": "Other/Unknown",
  "description": "Largish sparrow comparable to White-crowned Sparrow is size and shape.\u00a0 Underparts, neck, and face below the eyes were uniformly medium gray and unmarked.\u00a0 The most obvious plumage feature was the golden crown patch offset by a modestly thick black border.\u00a0 The border seemed to be extending down to the eye, so I think the bird must have been transitioning into breeding plumage at the time.",
  "photographer": "Photographer: Doug Faulkner",
  "photos_text": "Photos |",
  "uploads_text": "2544_GCSP_RedRocks_Jefferson_CO_18Feb2013_DWF_1.jpg",
  "date_submitted": "8/20/2013 8:38:00 PM",
  "attachments": [
    {
      "filename": "2544_GCSP_RedRocks_Jefferson_CO_18Feb2013_DWF_1.jpg",
      "url": "/RecordUploads/2544/2544_GCSP_RedRocks_Jefferson_CO_18Feb2013_DWF_1.jpg"
    }
  ]
}