{
  "doc_id": "14412",
  "scraped_at": "2026-06-13T14:44:15.362234",
  "species": "Golden-winged Warbler",
  "acc_no": "1997-080",
  "reporter_name": "Mark Janos",
  "address": "",
  "city": "",
  "state": "",
  "zip": "",
  "reporter_email": "",
  "other_observers": "",
  "species_name": "Golden-winged Warbler",
  "first_date": "5/11/1997 3:00:00 PM",
  "last_date": "5/12/1997 8:00:00 AM",
  "duration": "",
  "county": "Crowley",
  "specific_location": "Lake Henry",
  "number_of_birds": "1",
  "age": "Unknown",
  "sex": "Unknown",
  "plumage": "Other/Unknown",
  "description": "",
  "photographer": "Photographer: Mark Janos",
  "photos_text": "PDF",
  "uploads_text": "14412_gwwa-1997-80.pdf",
  "date_submitted": "11/26/2024 9:49:00 PM",
  "attachments": [
    {
      "filename": "14412_gwwa-1997-80.pdf",
      "url": "/RecordUploads/14412/14412_gwwa-1997-80.pdf"
    }
  ]
}