{
  "doc_id": "14166",
  "scraped_at": "2026-06-13T14:42:45.945944",
  "species": "Yellow-throated Vireo",
  "acc_no": "51-87-65",
  "reporter_name": "Dan Bridges",
  "address": "",
  "city": "",
  "state": "",
  "zip": "",
  "reporter_email": "",
  "other_observers": "",
  "species_name": "Yellow-throated Vireo",
  "first_date": "9/28/1987 9:45:00 AM",
  "last_date": "9/28/1987 9:50:00 AM",
  "duration": "",
  "county": "Larimer",
  "specific_location": "Horsetooth Reservoir",
  "number_of_birds": "1",
  "age": "Unknown",
  "sex": "Unknown",
  "plumage": "Other/Unknown",
  "description": "",
  "photographer": "Photographer: Dan Bridges",
  "photos_text": "PDF",
  "uploads_text": "14166_ytvi-51-87-65.pdf",
  "date_submitted": "8/17/2024 5:49:00 PM",
  "attachments": [
    {
      "filename": "14166_ytvi-51-87-65.pdf",
      "url": "/RecordUploads/14166/14166_ytvi-51-87-65.pdf"
    }
  ]
}