{
  "doc_id": "3948",
  "scraped_at": "2026-06-13T14:36:45.442499",
  "species": "Painted Redstart",
  "acc_no": "2014-046",
  "reporter_name": "Sue Riffe",
  "address": "96 Antelope Dr.,",
  "city": "LYONS,",
  "state": "CO",
  "zip": "80540-9023",
  "reporter_email": "sheflew@gmail.com",
  "other_observers": "Many other observers",
  "species_name": "Painted Redstart",
  "first_date": "5/2/2014 7:40:00 AM",
  "last_date": "5/2/2014 8:15:00 AM",
  "duration": "35",
  "county": "Weld",
  "specific_location": "Crow Valley Campground",
  "number_of_birds": "1",
  "age": "Adult",
  "sex": "Unknown",
  "plumage": "Breeding",
  "description": "When I arrived near the area seen, I heard it's breading song. It sang this song about two times a minute for most of the observation.\n\r\nWarbler sized bird seen feeding from the tops of the grove trees. It would fly and catch small flying insects the size of gnats and return to one of about four trees in this area. It almost always staid near or at the top of the trees. While landing and taking off from the trres, it would flash its tail feathers were several white feathers on each side were observed.\n\r\nIt is an all black warbler sized bird, black thin bill, small white crescent below the eye, bold wide white wing patch and an unmistakable bright red belly. The white wing patch and tail feathers were often on display while catching insects.\n\r\nWhat a beautiful bird!",
  "photographer": "Photographer: Sue Riffe",
  "photos_text": "Photos |",
  "uploads_text": "3948_Painted_Redstart_at_Crow_Valley_Campground_CO_5.2.14_DSC_8758_-_Copy.JPG",
  "date_submitted": "5/3/2014 8:11:00 AM",
  "attachments": [
    {
      "filename": "3948_Painted_Redstart_at_Crow_Valley_Campground_CO_5.2.14_DSC_8758_-_Copy.JPG",
      "url": "/RecordUploads/3948/3948_Painted_Redstart_at_Crow_Valley_Campground_CO_5.2.14_DSC_8758_-_Copy.JPG"
    }
  ]
}