{
  "doc_id": "13764",
  "scraped_at": "2026-06-13T14:34:54.010805",
  "species": "Ruff",
  "acc_no": "2003-018",
  "reporter_name": "Stan Oswald, Rachel Hopper, Larry Semo, Tony Leukering, Peter Gent",
  "address": "",
  "city": "",
  "state": "",
  "zip": "",
  "reporter_email": "",
  "other_observers": "",
  "species_name": "Ruff",
  "first_date": "10/5/2002 2:00:00 PM",
  "last_date": "10/6/2002 4:30:00 PM",
  "duration": "",
  "county": "Crowley",
  "specific_location": "Lake Meredith",
  "number_of_birds": "1",
  "age": "Unknown",
  "sex": "Unknown",
  "plumage": "Other/Unknown",
  "description": "",
  "photographer": "Photographer: Stan Oswald, Rachel Hopper, Larry Semo, Tony Leuke",
  "photos_text": "PDF",
  "uploads_text": "13764_ruff-2003-18.pdf",
  "date_submitted": "2/29/2024 8:31:00 PM",
  "attachments": [
    {
      "filename": "13764_ruff-2003-18.pdf",
      "url": "/RecordUploads/13764/13764_ruff-2003-18.pdf"
    }
  ]
}