{
  "acc_no": "N-26-72",
  "year": "1976",
  "location": "South Republican SWA",
  "county": "Yuma",
  "observers": "Mike Moulton, Peter Gent, Bruce Webb",
  "comments": "",
  "citations": "Andrews, R.  1976-1977 Report of the CBRC. Western Birds, 10, 57-70.  Webb, B., A Groove-billed Ani in Northeastern Colorado. Western Birds, 7, 153-154, 1976.",
  "documentations": [
    {
      "doc_id": "13226",
      "reporter": "Mike Moulton, Peter Gent",
      "date": "10/3/1976",
      "has_photos": false,
      "doc_url": "https://cobrc.org/Reports/PrintDoc.aspx?DocID=13226"
    }
  ],
  "scraped_at": "2026-06-13T14:35:15.021185"
}