{
  "doc_id": "743",
  "scraped_at": "2026-06-13T14:33:24.866008",
  "species": "Great-tailed Grackle",
  "acc_no": "2007-042",
  "reporter_name": "Doug Faulkner",
  "address": "6035 Parfet St.,",
  "city": "ARVADA,",
  "state": "CO",
  "zip": "80004-4648",
  "reporter_email": "zebrilus@gmail.com",
  "other_observers": "About 15 CFO convention field trip participants, including Ed Hollowed and Carol Blackard.;",
  "species_name": "Great-tailed Grackle",
  "first_date": "6/8/2007",
  "last_date": "",
  "duration": "about 5 minutes",
  "county": "Rio Blanco",
  "specific_location": "Rio Blanco SWA",
  "number_of_birds": "1",
  "age": "Unknown",
  "sex": "Male",
  "plumage": "Other/Unknown",
  "description": "General impression of a very large Common Grackle. Differing from Common Grackle, this bird had an extremely long tail, approximately the same length as the body. The all-black bill was also much longer and deeper than expected for a Common. Otherwise, the black plumage had a glossy purplish-blue sheen, more obvious on the head, mantle, and wing coverts than the rest of the body. It also had yellow eyes and black legs. In flight, the tail was deeply v-shaped.Behaviors: Walking along the edge of Rio Blanco SWA lake, eventually flying to a small patch of cattails in the northwest corner.Call: None heard.Plumage: adult",
  "photographer": "Photographer: Carol Blackard",
  "photos_text": "Photos |",
  "uploads_text": "743_xvtc1.jpg",
  "date_submitted": "7/3/2007 4:07:00 PM",
  "attachments": [
    {
      "filename": "743_xvtc1.jpg",
      "url": "/RecordUploads/743/743_xvtc1.jpg"
    }
  ]
}