{
  "doc_id": "13980",
  "scraped_at": "2026-06-13T14:38:56.767510",
  "species": "Scott's Oriole",
  "acc_no": "2024-018",
  "reporter_name": "Sally Waterhouse",
  "address": "13623 County Road 261L,",
  "city": "Nathrop,",
  "state": "CO",
  "zip": "81236-7713",
  "reporter_email": "smwaterh@owu.edu",
  "other_observers": "Preston Larimer and Greg Mihalik",
  "species_name": "Scott's Oriole",
  "first_date": "5/10/2024 10:10:00 AM",
  "last_date": "5/10/2024 12:05:00 PM",
  "duration": "40 minutes off and on",
  "county": "Chaffee",
  "specific_location": "Salida",
  "number_of_birds": "1",
  "age": "Adult",
  "sex": "Male",
  "plumage": "Breeding",
  "description": "Property owner who requested privacy had posted a photo of bird on May 09. 2024 to the \"Colorado Loves BIrds\" website wondering what it was. \u00a0Paul Hurtado checks this site and based on the poor photo thought Scott's or hybrid was possible and contacted me since he knows me and knows I live nearby. \u00a0I eventually made contact with the property owner and received permission to visit along with 2 other birders mid morning the next day. \u00a0She allowed us to stand in the backyard and view.\u00a0The bird was present as we arrived along with 16 other species (see ebird checklist of same day which I will post after submitting this report) eventually observed in the yard. \u00a0There was some snow falling/melting off branches from the late season 8 inch snowfall the night before as can be seen in photos. \u00a0The bird mostly flew back and forth from a thick spruce tree to a feeder with oranges.Jet black hood and black wings with lemon yellow belly extending under most of tail, lower back,\u00a0and lesser coverts edged below with 2 white wing bars was distinctive and clearly indicated a pure Scott's adult male in breeding plumage with no hybrid traits.\u00a0I stayed in touch with the property owner who indicated that the last day the bird was present was May 14. \u00a0Photos courtesy of Greg Mihalik",
  "photographer": "Photographer: Greg Mihalik, Greg Mihalik, Greg Mihalik",
  "photos_text": "Photos |",
  "uploads_text": "13980_gkiihegopiggephm.jpg\n13980_iocdnlcmifobclck.jpg\n13980_lilfinpnfkognldm.jpg",
  "date_submitted": "6/4/2024 1:58:00 PM",
  "attachments": [
    {
      "filename": "13980_gkiihegopiggephm.jpg",
      "url": "/RecordUploads/13980/13980_gkiihegopiggephm.jpg"
    },
    {
      "filename": "13980_iocdnlcmifobclck.jpg",
      "url": "/RecordUploads/13980/13980_iocdnlcmifobclck.jpg"
    },
    {
      "filename": "13980_lilfinpnfkognldm.jpg",
      "url": "/RecordUploads/13980/13980_lilfinpnfkognldm.jpg"
    }
  ]
}