{
  "doc_id": "524",
  "scraped_at": "2026-06-13T14:33:03.768941",
  "species": "'Cackling' Cackling Goose",
  "acc_no": "2002-172",
  "reporter_name": "Andrew Spencer",
  "address": "3649 E. Phillips Ave.,",
  "city": "CENTENNIAL,",
  "state": "CO",
  "zip": "80122-3642",
  "reporter_email": "gwwarbler@gmail.com",
  "other_observers": "Tina Jones; found and identified by me",
  "species_name": "'Cackling' Cackling Goose",
  "first_date": "1/13/2002",
  "last_date": "",
  "duration": "about 30 minutes",
  "county": "Arapahoe",
  "specific_location": "Fairmount Cemetery",
  "number_of_birds": "1",
  "age": "Unknown",
  "sex": "Unknown",
  "plumage": "Other/Unknown",
  "description": "the bird was a tiny goose, much smaller (at most half the size) of nearby Greater Canada Geese. The overall shape was more stocky, mostly due to a relatively shorter neck. The head shape was somwhat blocky, though the head also looked relatively smaller in comparison to Canada Goose. The bill was black, and relatively smaller in comparison to the head than nearby geese. The eye was dark, as were the legs.  The bird's plumage was similar to nearby Canada Geese, with the exception of a thin white neck band at the base of the neck, and overall a much darker color. This was especially evident on the breast, which was extremely dark, almost a glossy dark brownish-purple.Behaviors: the bird was hanging out with a flock of Canada Geese on a cemetery lawn, and was very shy, much more so than the Canada GeeseCall: none heardPlumage: adult",
  "photographer": "Photographer: Andrew Spencer, Andrew Spencer, Andrew Spencer, Andrew Spencer, Andrew Spencer",
  "photos_text": "Photos |",
  "uploads_text": "524_cfxm3.jpg\n524_cxhn1.jpg\n524_ubts2.jpg\n524_wgxr5.jpg\n524_ywqp4.jpg",
  "date_submitted": "8/15/2006 11:10:00 PM",
  "attachments": [
    {
      "filename": "524_cfxm3.jpg",
      "url": "/RecordUploads/524/524_cfxm3.jpg"
    },
    {
      "filename": "524_cxhn1.jpg",
      "url": "/RecordUploads/524/524_cxhn1.jpg"
    },
    {
      "filename": "524_ubts2.jpg",
      "url": "/RecordUploads/524/524_ubts2.jpg"
    },
    {
      "filename": "524_wgxr5.jpg",
      "url": "/RecordUploads/524/524_wgxr5.jpg"
    },
    {
      "filename": "524_ywqp4.jpg",
      "url": "/RecordUploads/524/524_ywqp4.jpg"
    }
  ]
}