{
  "doc_id": "2713",
  "scraped_at": "2026-06-13T14:41:22.127939",
  "species": "Ruddy Turnstone",
  "acc_no": "2000-032",
  "reporter_name": "Mark Janos",
  "address": "",
  "city": "",
  "state": "",
  "zip": "",
  "reporter_email": "",
  "other_observers": "",
  "species_name": "Ruddy Turnstone",
  "first_date": "5/6/2000",
  "last_date": "",
  "duration": "",
  "county": "Bent",
  "specific_location": "John Martin Reservoir State Park",
  "number_of_birds": "1",
  "age": "Unknown",
  "sex": "Unknown",
  "plumage": "Other/Unknown",
  "description": "",
  "photographer": "Photographer: Mark Janos",
  "photos_text": "",
  "uploads_text": "Doc2713_2000-32_Janos.pdf",
  "date_submitted": "11/22/2013 9:59:00 AM",
  "attachments": [
    {
      "filename": "Doc2713_2000-32_Janos.pdf",
      "url": "/RecordUploads/2713/Doc2713_2000-32_Janos.pdf"
    }
  ]
}