{
  "doc_id": "858",
  "scraped_at": "2026-06-13T14:47:28.005360",
  "species": "Red Phalarope",
  "acc_no": "2007-092",
  "reporter_name": "Bill Maynard",
  "address": "1390 Farnham Pt. # 205,",
  "city": "COLORADO SPRINGS,",
  "state": "CO",
  "zip": "80904-5215",
  "reporter_email": "bmaynard99@gmail.com",
  "other_observers": "Glenn Walbek found the bird near the dam, earlier in the day. Mark Peterson spotted it in the northeastern most corner.; Glenn Walbek was the original finder.",
  "species_name": "Red Phalarope",
  "first_date": "11/6/2007",
  "last_date": "",
  "duration": "4 minutes",
  "county": "Arapahoe",
  "specific_location": "Cherry Creek State Recreation Area",
  "number_of_birds": "1",
  "age": "Unknown",
  "sex": "Unknown",
  "plumage": "Other/Unknown",
  "description": "After hearing of a possible Red Phalarope and other interesting birds (3 loon species), Mark Peterson and I traveled to Cherry Creek Reservoir to look for them. After searching most of the reservoir's surface waters, we found ourselves in the far northeast corner as light was fading.  Mark spotted the bird, on the shoreline, close to us.  The bird was a large white-and-gray phalarope. The legs wiere grayish and seemed a bit short, but maybe that was because it was seen walking.   The face was distinctive, dark gray crown, wide dark mask, completely covering its eye, stoutly-based bill with a hint of yellow at the base on the mandible. The breast, throat, chin, and belly was white, with no other colors showing. The back, uppertail coverts, and dorsal surface of the tail was light gray, darkening on the hind neck and crown. The forehead was whitish.   We focused on the mask. It was broad towards its hindneck, tapering in width towards the bill.   The bird did flush onece, and I could see a wide white wing stripe that contrasted strongly with the rest of the gray wing. In flight the back appeared pure gray.Behaviors: It wattled on the shore in an side-to-side gate, occasionally gleaning \"stuff\" off the shoreline sand.Call: non heardPlumage: basic",
  "photographer": "Photographer:",
  "photos_text": "",
  "uploads_text": "No files uploaded.",
  "date_submitted": "12/27/2007 4:05:00 PM",
  "attachments": []
}