{
  "doc_id": "39",
  "scraped_at": "2026-06-13T14:43:15.270918",
  "species": "Yellow-throated Vireo",
  "acc_no": "2005-164",
  "reporter_name": "Roger Linfield",
  "address": "",
  "city": "",
  "state": "",
  "zip": "",
  "reporter_email": "",
  "other_observers": "Brenda Linfield; I believe that I was the original finder of this bird.  Peter Gent arrived not long after I first saw the bird. The bird had gone by then. However, Peter subsequently told me that he refound the bird one hour later.",
  "species_name": "Yellow-throated Vireo",
  "first_date": "5/23/2004",
  "last_date": "",
  "duration": "30 minutes",
  "county": "Boulder",
  "specific_location": "CU campus",
  "number_of_birds": "1",
  "age": "Unknown",
  "sex": "Unknown",
  "plumage": "Other/Unknown",
  "description": "The bird was near the top of an 80' tall deciduous tree, singing loudly.  The song was clearly vireo-like, with a hoarse two-note phrase, a 5 - 10 second pause, and then the two-note phrase again.  The bird was larger than a Warbling Vireo, but with generally similar shape.  It had a bold white belly, unstreaked, and a bright yellow unstreaked breast.  The face showed bright yellow spectacles on a medium background (dark eye, solid medium dark nape and mantle).  The bill was dark, too thick for a warbler.  The wings were dark, but I could not see details from my viewing position.Behaviors: The bird perched near the top of a tall deciduous tree, sang, and then moved to a different perch. It did not move around quickly through foliage in the typical manner of a warbler.Call: The song was clearly vireo-like, with a hoarse two-note phrase, a 5 - 10 second pause, and then the two-note phrase again.Plumage: adult",
  "photographer": "Photographer:",
  "photos_text": "",
  "uploads_text": "No files uploaded.",
  "date_submitted": "1/30/2005 9:19:00 PM",
  "attachments": []
}